{
  "pnl_today": 0.0,
  "pnl_week": 0.0,
  "trades_today": 0,
  "trades_this_hour": 0,
  "consecutive_losses": 0,
  "last_loss_time": null,
  "last_win_time": null,
  "cooldowns": {},
  "positions": {
    "UNI": {
      "available": 1.093593,
      "hold": 0.0,
      "total": 1.093593,
      "usd_value": 9.4841852925
    },
    "AERO": {
      "available": 0.1,
      "hold": 0.0,
      "total": 0.1,
      "usd_value": 0.11392350000000001
    },
    "FET": {
      "available": 88.2,
      "hold": 0.0,
      "total": 88.2,
      "usd_value": 29.044260000000005
    },
    "HBAR": {
      "available": 1682.9,
      "hold": 0.0,
      "total": 1682.9,
      "usd_value": 302.43395899999996
    },
    "ZK": {
      "available": 0.21905562,
      "hold": 873.1,
      "total": 873.31905562,
      "usd_value": 45.0239639124891
    },
    "XRP": {
      "available": 0.00812,
      "hold": 0.0,
      "total": 0.00812,
      "usd_value": 0.019442122000000003
    },
    "BTC": {
      "available": 0.00068841,
      "hold": 0.0,
      "total": 0.00068841,
      "usd_value": 71.06818877865
    }
  },
  "cash_balances": {
    "USDC": 0.070462312468,
    "USDT": 2.33462704,
    "USD": 75.7032673970177
  },
  "open_orders": {
    "378d866b-0f73-4717-be51-a9dc93f7499f": {
      "order_id": "6d3264c0-9b73-4521-98b0-a497a1fcf2ef",
      "client_order_id": "378d866b-0f73-4717-be51-a9dc93f7499f",
      "product_id": "ZK-USD",
      "side": "sell",
      "status": "open",
      "quote_size_usd": 52.386,
      "base_size": 873.1,
      "filled_size": 0.0,
      "filled_value": 0.0,
      "created_time": "2025-11-11T06:05:42.206556Z",
      "first_seen": "2025-11-11T23:00:55.901263+00:00",
      "updated_at": "2025-11-12T04:24:01.415357+00:00"
    }
  },
  "recent_orders": [
    {
      "order_id": "d0ea3286-337c-4a45-a4de-560678882de5",
      "client_order_id": "coid_322a29620541e64b",
      "product_id": "AERO-USD",
      "side": "sell",
      "quote_size_usd": 72.83455000000001,
      "status": "closed",
      "route": "live_market",
      "filled_size": 0.0,
      "filled_price": 0.0,
      "fees": 0.0,
      "fills": [],
      "result_snapshot": {
        "success": true,
        "success_response": {
          "order_id": "d0ea3286-337c-4a45-a4de-560678882de5",
          "product_id": "AERO-USD",
          "side": "SELL",
          "client_order_id": "coid_322a29620541e64b",
          "attached_order_id": ""
        },
        "order_configuration": {
          "market_market_ioc": {
            "base_size": "63.3",
            "rfq_enabled": false,
            "rfq_disabled": false,
            "reduce_only": false
          }
        }
      },
      "first_seen": "2025-11-12T03:39:34.336622+00:00",
      "updated_at": "2025-11-12T03:39:34.336622+00:00",
      "closed_at": "2025-11-12T03:39:46.631019+00:00"
    }
  ],
  "last_reconcile_at": "2025-11-12T04:23:56.259566+00:00",
  "last_reset_date": "2025-11-12",
  "last_reset_hour": 4,
  "events": [
    {
      "at": "2025-11-12T02:26:38.506762+00:00",
      "event": "open_orders_sync",
      "open_orders": 1,
      "closed": [],
      "created": []
    },
    {
      "at": "2025-11-12T02:27:03.612378+00:00",
      "event": "reconcile",
      "positions": 7,
      "open_orders": 1,
      "orders_closed": [],
      "orders_seen": []
    },
    {
      "at": "2025-11-12T02:27:08.604392+00:00",
      "event": "open_orders_sync",
      "open_orders": 1,
      "closed": [],
      "created": []
    },
    {
      "at": "2025-11-12T02:27:33.621109+00:00",
      "event": "reconcile",
      "positions": 7,
      "open_orders": 1,
      "orders_closed": [],
      "orders_seen": []
    },
    {
      "at": "2025-11-12T02:27:38.467577+00:00",
      "event": "open_orders_sync",
      "open_orders": 1,
      "closed": [],
      "created": []
    },
    {
      "at": "2025-11-12T02:28:03.630812+00:00",
      "event": "reconcile",
      "positions": 7,
      "open_orders": 1,
      "orders_closed": [],
      "orders_seen": []
    },
    {
      "at": "2025-11-12T02:28:28.570642+00:00",
      "event": "open_orders_sync",
      "open_orders": 1,
      "closed": [],
      "created": []
    },
    {
      "at": "2025-11-12T02:28:33.626876+00:00",
      "event": "reconcile",
      "positions": 7,
      "open_orders": 1,
      "orders_closed": [],
      "orders_seen": []
    },
    {
      "at": "2025-11-12T02:28:39.204325+00:00",
      "event": "open_orders_sync",
      "open_orders": 1,
      "closed": [],
      "created": []
    },
    {
      "at": "2025-11-12T02:29:03.627633+00:00",
      "event": "reconcile",
      "positions": 7,
      "open_orders": 1,
      "orders_closed": [],
      "orders_seen": []
    },
    {
      "at": "2025-11-12T02:29:09.142499+00:00",
      "event": "open_orders_sync",
      "open_orders": 1,
      "closed": [],
      "created": []
    },
    {
      "at": "2025-11-12T03:19:16.923271+00:00",
      "event": "reconcile",
      "positions": 7,
      "open_orders": 1,
      "orders_closed": [],
      "orders_seen": []
    },
    {
      "at": "2025-11-12T03:19:21.834876+00:00",
      "event": "open_orders_sync",
      "open_orders": 1,
      "closed": [],
      "created": []
    },
    {
      "at": "2025-11-12T03:19:46.925648+00:00",
      "event": "reconcile",
      "positions": 7,
      "open_orders": 1,
      "orders_closed": [],
      "orders_seen": []
    },
    {
      "at": "2025-11-12T03:19:52.174426+00:00",
      "event": "open_orders_sync",
      "open_orders": 1,
      "closed": [],
      "created": []
    },
    {
      "at": "2025-11-12T03:20:16.927464+00:00",
      "event": "reconcile",
      "positions": 7,
      "open_orders": 1,
      "orders_closed": [],
      "orders_seen": []
    },
    {
      "at": "2025-11-12T03:20:21.817480+00:00",
      "event": "open_orders_sync",
      "open_orders": 1,
      "closed": [],
      "created": []
    },
    {
      "at": "2025-11-12T03:30:23.556128+00:00",
      "event": "reconcile",
      "positions": 7,
      "open_orders": 1,
      "orders_closed": [],
      "orders_seen": []
    },
    {
      "at": "2025-11-12T03:30:28.884072+00:00",
      "event": "open_orders_sync",
      "open_orders": 1,
      "closed": [],
      "created": []
    },
    {
      "at": "2025-11-12T03:39:10.351434+00:00",
      "event": "reconcile",
      "positions": 7,
      "open_orders": 1,
      "orders_closed": [],
      "orders_seen": []
    },
    {
      "at": "2025-11-12T03:39:15.894072+00:00",
      "event": "open_orders_sync",
      "open_orders": 1,
      "closed": [],
      "created": []
    },
    {
      "at": "2025-11-12T03:39:34.336622+00:00",
      "event": "order_opened",
      "order_key": "coid_322a29620541e64b",
      "product_id": "AERO-USD",
      "side": "sell",
      "quote_size_usd": 72.83455000000001
    },
    {
      "at": "2025-11-12T03:39:41.253847+00:00",
      "event": "reconcile",
      "positions": 7,
      "open_orders": 1,
      "orders_closed": [
        "coid_322a29620541e64b"
      ],
      "orders_seen": []
    },
    {
      "at": "2025-11-12T03:39:46.631019+00:00",
      "event": "open_orders_sync",
      "open_orders": 1,
      "closed": [
        "coid_322a29620541e64b"
      ],
      "created": []
    },
    {
      "at": "2025-11-12T03:40:11.257804+00:00",
      "event": "reconcile",
      "positions": 7,
      "open_orders": 1,
      "orders_closed": [],
      "orders_seen": []
    },
    {
      "at": "2025-11-12T03:40:16.974794+00:00",
      "event": "open_orders_sync",
      "open_orders": 1,
      "closed": [],
      "created": []
    },
    {
      "at": "2025-11-12T03:40:41.262769+00:00",
      "event": "reconcile",
      "positions": 7,
      "open_orders": 1,
      "orders_closed": [],
      "orders_seen": []
    },
    {
      "at": "2025-11-12T03:40:46.760515+00:00",
      "event": "open_orders_sync",
      "open_orders": 1,
      "closed": [],
      "created": []
    },
    {
      "at": "2025-11-12T03:41:11.267848+00:00",
      "event": "reconcile",
      "positions": 7,
      "open_orders": 1,
      "orders_closed": [],
      "orders_seen": []
    },
    {
      "at": "2025-11-12T03:41:16.779217+00:00",
      "event": "open_orders_sync",
      "open_orders": 1,
      "closed": [],
      "created": []
    },
    {
      "at": "2025-11-12T03:41:41.270435+00:00",
      "event": "reconcile",
      "positions": 7,
      "open_orders": 1,
      "orders_closed": [],
      "orders_seen": []
    },
    {
      "at": "2025-11-12T03:41:46.515452+00:00",
      "event": "open_orders_sync",
      "open_orders": 1,
      "closed": [],
      "created": []
    },
    {
      "at": "2025-11-12T03:42:11.274137+00:00",
      "event": "reconcile",
      "positions": 7,
      "open_orders": 1,
      "orders_closed": [],
      "orders_seen": []
    },
    {
      "at": "2025-11-12T03:42:16.308016+00:00",
      "event": "open_orders_sync",
      "open_orders": 1,
      "closed": [],
      "created": []
    },
    {
      "at": "2025-11-12T03:51:56.049957+00:00",
      "event": "reconcile",
      "positions": 7,
      "open_orders": 1,
      "orders_closed": [],
      "orders_seen": []
    },
    {
      "at": "2025-11-12T03:52:01.063812+00:00",
      "event": "open_orders_sync",
      "open_orders": 1,
      "closed": [],
      "created": []
    },
    {
      "at": "2025-11-12T03:52:26.054757+00:00",
      "event": "reconcile",
      "positions": 7,
      "open_orders": 1,
      "orders_closed": [],
      "orders_seen": []
    },
    {
      "at": "2025-11-12T03:52:31.693589+00:00",
      "event": "open_orders_sync",
      "open_orders": 1,
      "closed": [],
      "created": []
    },
    {
      "at": "2025-11-12T03:52:56.059465+00:00",
      "event": "reconcile",
      "positions": 7,
      "open_orders": 1,
      "orders_closed": [],
      "orders_seen": []
    },
    {
      "at": "2025-11-12T03:53:01.363780+00:00",
      "event": "open_orders_sync",
      "open_orders": 1,
      "closed": [],
      "created": []
    },
    {
      "at": "2025-11-12T03:53:26.064147+00:00",
      "event": "reconcile",
      "positions": 7,
      "open_orders": 1,
      "orders_closed": [],
      "orders_seen": []
    },
    {
      "at": "2025-11-12T03:53:31.652277+00:00",
      "event": "open_orders_sync",
      "open_orders": 1,
      "closed": [],
      "created": []
    },
    {
      "at": "2025-11-12T03:53:56.067750+00:00",
      "event": "reconcile",
      "positions": 7,
      "open_orders": 1,
      "orders_closed": [],
      "orders_seen": []
    },
    {
      "at": "2025-11-12T03:54:01.892710+00:00",
      "event": "open_orders_sync",
      "open_orders": 1,
      "closed": [],
      "created": []
    },
    {
      "at": "2025-11-12T03:54:26.071064+00:00",
      "event": "reconcile",
      "positions": 7,
      "open_orders": 1,
      "orders_closed": [],
      "orders_seen": []
    },
    {
      "at": "2025-11-12T03:54:31.532031+00:00",
      "event": "open_orders_sync",
      "open_orders": 1,
      "closed": [],
      "created": []
    },
    {
      "at": "2025-11-12T03:54:56.072247+00:00",
      "event": "reconcile",
      "positions": 7,
      "open_orders": 1,
      "orders_closed": [],
      "orders_seen": []
    },
    {
      "at": "2025-11-12T03:55:01.335138+00:00",
      "event": "open_orders_sync",
      "open_orders": 1,
      "closed": [],
      "created": []
    },
    {
      "at": "2025-11-12T03:55:26.077953+00:00",
      "event": "reconcile",
      "positions": 7,
      "open_orders": 1,
      "orders_closed": [],
      "orders_seen": []
    },
    {
      "at": "2025-11-12T03:55:31.213388+00:00",
      "event": "open_orders_sync",
      "open_orders": 1,
      "closed": [],
      "created": []
    },
    {
      "at": "2025-11-12T03:55:56.083727+00:00",
      "event": "reconcile",
      "positions": 7,
      "open_orders": 1,
      "orders_closed": [],
      "orders_seen": []
    },
    {
      "at": "2025-11-12T03:56:01.081295+00:00",
      "event": "open_orders_sync",
      "open_orders": 1,
      "closed": [],
      "created": []
    },
    {
      "at": "2025-11-12T03:56:26.135239+00:00",
      "event": "reconcile",
      "positions": 7,
      "open_orders": 1,
      "orders_closed": [],
      "orders_seen": []
    },
    {
      "at": "2025-11-12T03:56:31.325567+00:00",
      "event": "open_orders_sync",
      "open_orders": 1,
      "closed": [],
      "created": []
    },
    {
      "at": "2025-11-12T03:56:56.144558+00:00",
      "event": "reconcile",
      "positions": 7,
      "open_orders": 1,
      "orders_closed": [],
      "orders_seen": []
    },
    {
      "at": "2025-11-12T03:57:01.455370+00:00",
      "event": "open_orders_sync",
      "open_orders": 1,
      "closed": [],
      "created": []
    },
    {
      "at": "2025-11-12T03:57:26.144087+00:00",
      "event": "reconcile",
      "positions": 7,
      "open_orders": 1,
      "orders_closed": [],
      "orders_seen": []
    },
    {
      "at": "2025-11-12T03:57:31.218459+00:00",
      "event": "open_orders_sync",
      "open_orders": 1,
      "closed": [],
      "created": []
    },
    {
      "at": "2025-11-12T03:57:56.146246+00:00",
      "event": "reconcile",
      "positions": 7,
      "open_orders": 1,
      "orders_closed": [],
      "orders_seen": []
    },
    {
      "at": "2025-11-12T03:58:01.207392+00:00",
      "event": "open_orders_sync",
      "open_orders": 1,
      "closed": [],
      "created": []
    },
    {
      "at": "2025-11-12T03:58:26.150940+00:00",
      "event": "reconcile",
      "positions": 7,
      "open_orders": 1,
      "orders_closed": [],
      "orders_seen": []
    },
    {
      "at": "2025-11-12T03:58:31.385695+00:00",
      "event": "open_orders_sync",
      "open_orders": 1,
      "closed": [],
      "created": []
    },
    {
      "at": "2025-11-12T03:58:56.155573+00:00",
      "event": "reconcile",
      "positions": 7,
      "open_orders": 1,
      "orders_closed": [],
      "orders_seen": []
    },
    {
      "at": "2025-11-12T03:59:01.409960+00:00",
      "event": "open_orders_sync",
      "open_orders": 1,
      "closed": [],
      "created": []
    },
    {
      "at": "2025-11-12T03:59:26.159829+00:00",
      "event": "reconcile",
      "positions": 7,
      "open_orders": 1,
      "orders_closed": [],
      "orders_seen": []
    },
    {
      "at": "2025-11-12T03:59:31.414354+00:00",
      "event": "open_orders_sync",
      "open_orders": 1,
      "closed": [],
      "created": []
    },
    {
      "at": "2025-11-12T03:59:56.165068+00:00",
      "event": "reconcile",
      "positions": 7,
      "open_orders": 1,
      "orders_closed": [],
      "orders_seen": []
    },
    {
      "at": "2025-11-12T04:00:01.265871+00:00",
      "event": "open_orders_sync",
      "open_orders": 1,
      "closed": [],
      "created": []
    },
    {
      "at": "2025-11-12T04:00:26.169087+00:00",
      "event": "reconcile",
      "positions": 7,
      "open_orders": 1,
      "orders_closed": [],
      "orders_seen": []
    },
    {
      "at": "2025-11-12T04:00:31.488238+00:00",
      "event": "open_orders_sync",
      "open_orders": 1,
      "closed": [],
      "created": []
    },
    {
      "at": "2025-11-12T04:00:56.172388+00:00",
      "event": "reconcile",
      "positions": 7,
      "open_orders": 1,
      "orders_closed": [],
      "orders_seen": []
    },
    {
      "at": "2025-11-12T04:01:01.445963+00:00",
      "event": "open_orders_sync",
      "open_orders": 1,
      "closed": [],
      "created": []
    },
    {
      "at": "2025-11-12T04:01:26.177518+00:00",
      "event": "reconcile",
      "positions": 7,
      "open_orders": 1,
      "orders_closed": [],
      "orders_seen": []
    },
    {
      "at": "2025-11-12T04:01:31.476520+00:00",
      "event": "open_orders_sync",
      "open_orders": 1,
      "closed": [],
      "created": []
    },
    {
      "at": "2025-11-12T04:01:56.182542+00:00",
      "event": "reconcile",
      "positions": 7,
      "open_orders": 1,
      "orders_closed": [],
      "orders_seen": []
    },
    {
      "at": "2025-11-12T04:02:01.655053+00:00",
      "event": "open_orders_sync",
      "open_orders": 1,
      "closed": [],
      "created": []
    },
    {
      "at": "2025-11-12T04:17:46.374810+00:00",
      "event": "reconcile",
      "positions": 7,
      "open_orders": 1,
      "orders_closed": [],
      "orders_seen": []
    },
    {
      "at": "2025-11-12T04:17:51.539164+00:00",
      "event": "open_orders_sync",
      "open_orders": 1,
      "closed": [],
      "created": []
    },
    {
      "at": "2025-11-12T04:18:34.384814+00:00",
      "event": "reconcile",
      "positions": 7,
      "open_orders": 1,
      "orders_closed": [],
      "orders_seen": []
    },
    {
      "at": "2025-11-12T04:18:39.109908+00:00",
      "event": "open_orders_sync",
      "open_orders": 1,
      "closed": [],
      "created": []
    },
    {
      "at": "2025-11-12T04:19:18.285003+00:00",
      "event": "reconcile",
      "positions": 7,
      "open_orders": 1,
      "orders_closed": [],
      "orders_seen": []
    },
    {
      "at": "2025-11-12T04:19:23.266043+00:00",
      "event": "open_orders_sync",
      "open_orders": 1,
      "closed": [],
      "created": []
    },
    {
      "at": "2025-11-12T04:19:50.479085+00:00",
      "event": "reconcile",
      "positions": 7,
      "open_orders": 1,
      "orders_closed": [],
      "orders_seen": []
    },
    {
      "at": "2025-11-12T04:19:55.449381+00:00",
      "event": "open_orders_sync",
      "open_orders": 1,
      "closed": [],
      "created": []
    },
    {
      "at": "2025-11-12T04:20:23.077965+00:00",
      "event": "reconcile",
      "positions": 7,
      "open_orders": 1,
      "orders_closed": [],
      "orders_seen": []
    },
    {
      "at": "2025-11-12T04:20:28.041311+00:00",
      "event": "open_orders_sync",
      "open_orders": 1,
      "closed": [],
      "created": []
    },
    {
      "at": "2025-11-12T04:20:55.115796+00:00",
      "event": "reconcile",
      "positions": 7,
      "open_orders": 1,
      "orders_closed": [],
      "orders_seen": []
    },
    {
      "at": "2025-11-12T04:21:00.460885+00:00",
      "event": "open_orders_sync",
      "open_orders": 1,
      "closed": [],
      "created": []
    },
    {
      "at": "2025-11-12T04:21:27.372816+00:00",
      "event": "reconcile",
      "positions": 7,
      "open_orders": 1,
      "orders_closed": [],
      "orders_seen": []
    },
    {
      "at": "2025-11-12T04:21:32.802574+00:00",
      "event": "open_orders_sync",
      "open_orders": 1,
      "closed": [],
      "created": []
    },
    {
      "at": "2025-11-12T04:21:56.213476+00:00",
      "event": "reconcile",
      "positions": 7,
      "open_orders": 1,
      "orders_closed": [],
      "orders_seen": []
    },
    {
      "at": "2025-11-12T04:22:01.550285+00:00",
      "event": "open_orders_sync",
      "open_orders": 1,
      "closed": [],
      "created": []
    },
    {
      "at": "2025-11-12T04:22:25.128536+00:00",
      "event": "reconcile",
      "positions": 7,
      "open_orders": 1,
      "orders_closed": [],
      "orders_seen": []
    },
    {
      "at": "2025-11-12T04:22:30.112772+00:00",
      "event": "open_orders_sync",
      "open_orders": 1,
      "closed": [],
      "created": []
    },
    {
      "at": "2025-11-12T04:22:55.183737+00:00",
      "event": "reconcile",
      "positions": 7,
      "open_orders": 1,
      "orders_closed": [],
      "orders_seen": []
    },
    {
      "at": "2025-11-12T04:23:00.070991+00:00",
      "event": "open_orders_sync",
      "open_orders": 1,
      "closed": [],
      "created": []
    },
    {
      "at": "2025-11-12T04:23:27.956927+00:00",
      "event": "reconcile",
      "positions": 7,
      "open_orders": 1,
      "orders_closed": [],
      "orders_seen": []
    },
    {
      "at": "2025-11-12T04:23:32.925654+00:00",
      "event": "open_orders_sync",
      "open_orders": 1,
      "closed": [],
      "created": []
    },
    {
      "at": "2025-11-12T04:23:56.259566+00:00",
      "event": "reconcile",
      "positions": 7,
      "open_orders": 1,
      "orders_closed": [],
      "orders_seen": []
    },
    {
      "at": "2025-11-12T04:24:01.415357+00:00",
      "event": "open_orders_sync",
      "open_orders": 1,
      "closed": [],
      "created": []
    }
  ],
  "high_water_mark": 494.03608340685287,
  "last_open_orders_sync": "2025-11-12T04:24:01.415357+00:00"
}